IceImport.py
omero_API_ice.py
omero_Collections_ice.py
omero_Constants_ice.py
omero_FS_ice.py
omero_Internal_ice.py
omero_ModelF_ice.py
omero_ROMIO_ice.py
omero_RTypes_ice.py
omero_Repositories_ice.py
omero_Scripts_ice.py
omero_ServerErrors_ice.py
omero_ServicesF_ice.py
omero_SharedResources_ice.py
omero_SystemF_ice.py
omero_System_ice.py
omero_Tables_ice.py
omero_api_Exporter_ice.py
omero_api_IAdmin_ice.py
omero_api_IConfig_ice.py
omero_api_IContainer_ice.py
omero_api_ILdap_ice.py
omero_api_IMetadata_ice.py
omero_api_IPixels_ice.py
omero_api_IProjection_ice.py
omero_api_IQuery_ice.py
omero_api_IRenderingSettings_ice.py
omero_api_IRepositoryInfo_ice.py
omero_api_IRoi_ice.py
omero_api_IScript_ice.py
omero_api_ISession_ice.py
omero_api_IShare_ice.py
omero_api_ITimeline_ice.py
omero_api_ITypes_ice.py
omero_api_IUpdate_ice.py
omero_api_JobHandle_ice.py
omero_api_MetadataStore_ice.py
omero_api_PyramidService_ice.py
omero_api_RawFileStore_ice.py
omero_api_RawPixelsStore_ice.py
omero_api_RenderingEngine_ice.py
omero_api_Search_ice.py
omero_api_ThumbnailStore_ice.py
omero_cmd_API_ice.py
omero_cmd_Admin_ice.py
omero_cmd_Basic_ice.py
omero_cmd_FS_ice.py
omero_cmd_Graphs_ice.py
omero_cmd_Mail_ice.py
omero_model_AcquisitionModeI.py
omero_model_AcquisitionMode_ice.py
omero_model_AdminPrivilegeI.py
omero_model_AdminPrivilege_ice.py
omero_model_AffineTransformI.py
omero_model_AffineTransform_ice.py
omero_model_AnnotationAnnotationLinkI.py
omero_model_AnnotationAnnotationLink_ice.py
omero_model_AnnotationI.py
omero_model_Annotation_ice.py
omero_model_ArcI.py
omero_model_ArcTypeI.py
omero_model_ArcType_ice.py
omero_model_Arc_ice.py
omero_model_BasicAnnotationI.py
omero_model_BasicAnnotation_ice.py
omero_model_BinningI.py
omero_model_Binning_ice.py
omero_model_BooleanAnnotationI.py
omero_model_BooleanAnnotation_ice.py
omero_model_ChannelAnnotationLinkI.py
omero_model_ChannelAnnotationLink_ice.py
omero_model_ChannelBindingI.py
omero_model_ChannelBinding_ice.py
omero_model_ChannelI.py
omero_py-5.21.1.dist-info/licenses/LICENSE.txt
omero_py-5.21.1.dist-info/METADATA
omero_py-5.21.1.dist-info/WHEEL
omero_py-5.21.1.dist-info/entry_points.txt
omero_py-5.21.1.dist-info/top_level.txt
omero_py-5.21.1.dist-info/RECORD
