Metadata-Version: 2.4
Name: omero-py
Version: 5.21.1
Summary: Python bindings to the OMERO.blitz server
Home-page: https://github.com/ome/omero-py
Author: The Open Microscopy Team
Author-email: ome-devel@lists.openmicroscopy.org.uk
Project-URL: Documentation, https://docs.openmicroscopy.org/omero/latest/developers/Python.html
Project-URL: Bug tracker, https://github.com/ome/omero-py/issues
Project-URL: API, https://omero-py.readthedocs.io/
Classifier: Development Status :: 5 - Production/Stable
Classifier: Intended Audience :: Developers
Classifier: Intended Audience :: Science/Research
Classifier: Intended Audience :: System Administrators
Classifier: License :: OSI Approved :: GNU General Public License v2 or later (GPLv2+)
Classifier: Natural Language :: English
Classifier: Operating System :: OS Independent
Classifier: Programming Language :: Python :: 3
Classifier: Topic :: Software Development :: Libraries :: Python Modules
Requires-Python: >=3.8
License-File: LICENSE.txt
Requires-Dist: appdirs
Requires-Dist: future
Requires-Dist: numpy<2; python_version < "3.10"
Requires-Dist: numpy<3; python_version >= "3.10"
Requires-Dist: Pillow>=10.0.0
Requires-Dist: PyYAML
Requires-Dist: zeroc-ice<3.7,>=3.6.5
Requires-Dist: pywin32; platform_system == "Windows"
Requires-Dist: requests
Requires-Dist: portalocker
Dynamic: author
Dynamic: author-email
Dynamic: classifier
Dynamic: description
Dynamic: home-page
Dynamic: license-file
Dynamic: project-url
Dynamic: requires-dist
Dynamic: requires-python
Dynamic: summary
